frelpt/__init__.py
tests/__init__.py
tests/test_units.py
frelpt-0.0.1.dist-info/LICENSE
frelpt-0.0.1.dist-info/METADATA
frelpt-0.0.1.dist-info/WHEEL
frelpt-0.0.1.dist-info/top_level.txt
frelpt-0.0.1.dist-info/RECORD
